yndx_disk/__init__.py
yndx_disk/classes.py
yndx_disk/api/__init__.py
yndx_disk/api/disk.py
yndx_disk/api/exceptions.py
yndx_disk/api/operations.py
yndx_disk/api/public_resources.py
yndx_disk/api/resources.py
yndx_disk/api/trash_resources.py
yndx_disk/api/utils.py
yndx_disk/clients/__init__.py
yndx_disk/clients/async_client.py
yndx_disk/clients/sync_client.py
yndx_disk-0.3.1.dist-info/METADATA
yndx_disk-0.3.1.dist-info/WHEEL
yndx_disk-0.3.1.dist-info/top_level.txt
yndx_disk-0.3.1.dist-info/RECORD
